healthmetaverse/__init__.py
healthmetaverse/topicmodel.py
healthmetaverse/wordcloud.py
healthmetaverse/__pycache__/__init__.cpython-36.pyc
healthmetaverse/__pycache__/topicmodel.cpython-36.pyc
healthmetaverse/data/metaverse-news.txt
health_metaverse-0.0.3.dist-info/LICENSE
health_metaverse-0.0.3.dist-info/METADATA
health_metaverse-0.0.3.dist-info/WHEEL
health_metaverse-0.0.3.dist-info/top_level.txt
health_metaverse-0.0.3.dist-info/RECORD
