Metadata-Version: 2.1
Name: health-metaverse
Version: 0.0.3
Summary: Health Metaverse: Concept, Framework and Applications
Home-page: https://health-metaverse.github.io/
Author: Donghua Chen
Author-email: douglaschan@126.com
License: UNKNOWN
Project-URL: Leave a feedback, https://github.com/Health-Metaverse/health-metaverse.github.io/issues
Keywords: metaverse,health metaverse,medical metaverse,virtual worlds,healthcare,medical informatics
Platform: UNKNOWN
Classifier: Development Status :: 3 - Alpha
Classifier: Intended Audience :: Developers
Classifier: Topic :: Software Development :: Build Tools
Classifier: License :: OSI Approved :: MIT License
Classifier: Programming Language :: Python :: 3
Classifier: Programming Language :: Python :: 3.6
Classifier: Programming Language :: Python :: 3.7
Classifier: Programming Language :: Python :: 3.8
Classifier: Programming Language :: Python :: 3.9
Classifier: Programming Language :: Python :: 3 :: Only
Requires-Python: >=3.6, <4
License-File: LICENSE
Requires-Dist: nltk
Requires-Dist: stop-words
Requires-Dist: gensim
Requires-Dist: pandas
Provides-Extra: dev
Requires-Dist: check-manifest ; extra == 'dev'
Provides-Extra: test
Requires-Dist: coverage ; extra == 'test'
